calculator_api/__init__.py
calculator_api/main.py
calculator_api/src/__init__.py
calculator_api/src/calculator_utils.py
calculator_api-1.6.0.dist-info/METADATA
calculator_api-1.6.0.dist-info/WHEEL
calculator_api-1.6.0.dist-info/RECORD
